essay_spider_xhs_mcp_server_lc/API实例文件
essay_spider_xhs_mcp_server_lc/__init__.py
essay_spider_xhs_mcp_server_lc/server.py
essay_spider_xhs_mcp_server_lc-0.1.7.dist-info/METADATA
essay_spider_xhs_mcp_server_lc-0.1.7.dist-info/WHEEL
essay_spider_xhs_mcp_server_lc-0.1.7.dist-info/entry_points.txt
essay_spider_xhs_mcp_server_lc-0.1.7.dist-info/RECORD
