Metadata-Version: 2.4
Name: essay-spider-xhs-mcp-server-lc
Version: 0.1.7
Summary: Add your description here
Author-email: Melle_lichao <lichao10060909@163.com>
Requires-Python: >=3.11
Requires-Dist: dashscope>=1.23.3
Requires-Dist: mcp[cli]>=1.8.1
Requires-Dist: openai>=1.78.1
Requires-Dist: python-docx>=1.1.2
